setup.cfg
setup.py
tornfoursquare/__init__.py
tornfoursquare.egg-info/PKG-INFO
tornfoursquare.egg-info/SOURCES.txt
tornfoursquare.egg-info/dependency_links.txt
tornfoursquare.egg-info/entry_points.txt
tornfoursquare.egg-info/not-zip-safe
tornfoursquare.egg-info/top_level.txt