Metadata-Version: 1.0
Name: tornfoursquare
Version: 0.0.1
Summary: Foursquare auth wrapper for Tornado Web
Home-page: https://github.com/stevepeak/tornfoursquare
Author: @iopeak
Author-email: steve@stevepeak.net
License: Apache v2
Keywords: tornado tornadoweb foursquare
Platform: UNKNOWN
